setup.py
grma/__init__.py
grma/app.py
grma/config.py
grma/mayue.py
grma/pidfile.py
grma/utils.py
grma/worker.py
grma.egg-info/PKG-INFO
grma.egg-info/SOURCES.txt
grma.egg-info/dependency_links.txt
grma.egg-info/entry_points.txt
grma.egg-info/not-zip-safe
grma.egg-info/requires.txt
grma.egg-info/top_level.txt
grma/server/__init__.py
grma/server/base.py