Metadata-Version: 1.0
Name: grma
Version: 0.0.5
Summary: Simple gRPC Python manager
Home-page: https://github.com/qiajigou/grma
Author: GuoJing
Author-email: soundbbg@gmail.com
License: MIT
Platform: UNKNOWN
